ego_algotrading/__init__.py
ego_algotrading/base.cpython-310-x86_64-linux-gnu.so
ego_algotrading/engine.cpython-310-x86_64-linux-gnu.so
ego_algotrading/template.cpython-310-x86_64-linux-gnu.so
ego_algotrading/algos/__init__.py
ego_algotrading/algos/best_limit_algo.cpython-310-x86_64-linux-gnu.so
ego_algotrading/algos/dma_algo.cpython-310-x86_64-linux-gnu.so
ego_algotrading/algos/iceberg_algo.cpython-310-x86_64-linux-gnu.so
ego_algotrading/algos/sniper_algo.cpython-310-x86_64-linux-gnu.so
ego_algotrading/algos/stop_algo.cpython-310-x86_64-linux-gnu.so
ego_algotrading/algos/twap_algo.cpython-310-x86_64-linux-gnu.so
ego_algotrading/ui/__init__.py
ego_algotrading/ui/algo.png
ego_algotrading/ui/display.cpython-310-x86_64-linux-gnu.so
ego_algotrading/ui/widget.cpython-310-x86_64-linux-gnu.so
ego_chartwizard/__init__.py
ego_chartwizard/engine.cpython-310-x86_64-linux-gnu.so
ego_chartwizard/ui/__init__.py
ego_chartwizard/ui/cw.png
ego_chartwizard/ui/widget.cpython-310-x86_64-linux-gnu.so
ego_ctabacktester/__init__.py
ego_ctabacktester/engine.cpython-310-x86_64-linux-gnu.so
ego_ctabacktester/ui/__init__.py
ego_ctabacktester/ui/backtester.png
ego_ctabacktester/ui/widget.cpython-310-x86_64-linux-gnu.so
ego_ctastrategy/__init__.py
ego_ctastrategy/backtesting.cpython-310-x86_64-linux-gnu.so
ego_ctastrategy/base.cpython-310-x86_64-linux-gnu.so
ego_ctastrategy/engine.cpython-310-x86_64-linux-gnu.so
ego_ctastrategy/kjf.cpython-310-x86_64-linux-gnu.so
ego_ctastrategy/template.cpython-310-x86_64-linux-gnu.so
ego_ctastrategy/strategies/__init__.py
ego_ctastrategy/strategies/gt_ib_xm.so
ego_ctastrategy/strategies/gt_laser_ib.so
ego_ctastrategy/ui/__init__.py
ego_ctastrategy/ui/cta.png
ego_ctastrategy/ui/rollover.cpython-310-x86_64-linux-gnu.so
ego_ctastrategy/ui/widget.cpython-310-x86_64-linux-gnu.so
ego_ctp/__init__.py
ego_ctp/api/__init__.py
ego_ctp/api/ctp_constant.so
ego_ctp/api/libthostmduserapi_se.so
ego_ctp/api/libthosttraderapi_se.so
EGOPY-1.3.202403.dist-info/LICENSE
EGOPY-1.3.202403.dist-info/METADATA
EGOPY-1.3.202403.dist-info/WHEEL
EGOPY-1.3.202403.dist-info/top_level.txt
EGOPY-1.3.202403.dist-info/RECORD
